{
  "CADETPath": "C:/Users/kosh_000/CADET/cadet/bin/cadet-cli.exe",
  "baseDir": "C:/Users/kosh_000/Documents/Visual Studio 2017/Projects/CADETMatch/Examples/MCMC/Dextran",
  "resultsDir": "nsga3_mcmc_1000/",
  "tempDir": "L:/",
  "CSV": "dextran_MCMC.csv",
    "checkpointFile": "check",
    "searchMethod": "NSGA3",
    "population": 500,
    "finalGradRefinement": 0,
    "stallGenerations": 10,
    "continueMCMC": 1,
    "normalizeOutput": 0,
  "kde_synthetic": [
		{
			"file_path": "dextran_pulse.h5",
			"experimental_csv": "dextran_pulse.csv",
			"name": "main",
			"units": [
				1
			],
			"delay": [
				0.0,
				3.0
			],
			"flow": [
				1.0,
				0.03
			],
			"load": [
				1.0,
				0.03
			],
			"error_slope": [
				1.0,
				0.001
			],
			"error_base": 50.0,
			"base": 50.0,
			"count": 1000
		}
	],
  "parameters": [
    {
      "transform": "norm_log",
      "component": -1,
      "bound": -1,
      "location": "/input/model/unit_001/COL_DISPERSION",
      "min": 1e-9,
      "max": 1e-5
    },
    {
      "transform": "norm",
      "component": -1,
      "bound": -1,
      "location": "/input/model/unit_001/COL_POROSITY",
      "min": 0.3,
      "max": 0.5
    }
  ],
  "experiments": [
    {
      "CSV": "dextran_pulse.csv",
      "isotherm": "/output/solution/unit_001/SOLUTION_OUTLET_COMP_000",
      "HDF5": "dextran_pulse.h5",
      "name": "main",
      "features": [
        {
			"name": "Pulse",
			"type": "DextranShape"
		}
      ]
    }
  ]
}
